depwatch/__init__.py
depwatch/command.py
depwatch/date_utils.py
depwatch/deployment.py
depwatch/exception.py
depwatch/history.py
depwatch/main.py
depwatch/repository.py
depwatch/writer.py
depwatch-0.1.3.dist-info/entry_points.txt
depwatch-0.1.3.dist-info/WHEEL
depwatch-0.1.3.dist-info/METADATA
depwatch-0.1.3.dist-info/licenses/LICENSE
depwatch-0.1.3.dist-info/RECORD
