Metadata-Version: 2.1
Name: depwatch
Version: 0.1.3
Summary: A Simple command-line tool for collecting the times of various events in a project's lifecycle
License: MIT
Author-email: hamakou108 <hamakou108@gmail.com>
Requires-Python: >=3.11
Classifier: Programming Language :: Python :: 3
Requires-Dist: PyGithub>=1.58
Requires-Dist: pycircleci>=0.7
Requires-Dist: python-dotenv>=1.0
Requires-Dist: requests>=2.31
Requires-Dist: typer[all]>=0.9
Requires-Dist: types-requests>=2.31
